Metadata-Version: 2.1
Name: modern-python-project
Version: 0.3.0
Summary: Testing modern python tools
Home-page: https://github.com/LuckyDams/modern-python-project.git
License: MIT
Keywords: modern,python,project,tools
Author: LuckyDams
Author-email: luckydams@gmail.com
Requires-Python: >=3.7,<4.0
Classifier: License :: OSI Approved :: MIT License
Classifier: Programming Language :: Python :: 3
Classifier: Programming Language :: Python :: 3.7
Classifier: Programming Language :: Python :: 3.8
Requires-Dist: click (>=7.0,<8.0)
Requires-Dist: desert (>=2020.1.6,<2021.0.0)
Requires-Dist: importlib_metadata (>=1.6.1,<2.0.0); python_version < "3.8"
Requires-Dist: marshmallow (>=3.6.0,<4.0.0)
Requires-Dist: requests (>=2.23.0,<3.0.0)
Project-URL: Documentation, https://modern-python-project.readthedocs.io
Project-URL: Repository, https://github.com/LuckyDams/modern-python-project.git
